todays_holidays/__init__.py
todays_holidays-0.1.dist-info/LICENSE
todays_holidays-0.1.dist-info/METADATA
todays_holidays-0.1.dist-info/WHEEL
todays_holidays-0.1.dist-info/top_level.txt
todays_holidays-0.1.dist-info/RECORD
