Metadata-Version: 2.1
Name: todays-holidays
Version: 0.1
Summary: For telling today/tomorrows holliday
Home-page: UNKNOWN
Author: Samuel Halperin
Author-email: spshalperin@gmail.com
License: UNKNOWN
Platform: UNKNOWN
